bracelogger.py
bracelogger-1.1.1.dist-info/METADATA
bracelogger-1.1.1.dist-info/WHEEL
bracelogger-1.1.1.dist-info/top_level.txt
bracelogger-1.1.1.dist-info/RECORD
